[
  {
    "name": "class",
    "admin": false,
    "required": ["Name|Class"],
    "optional": [],
    "description": "Lists the class of the specified roster member *OR* Lists all roster members of the specified class."
  },
  {
    "name": "groups",
    "admin": false,
    "required": [],
    "optional": [],
    "description": "Lists all available groups and their members."
  },
  {
    "name": "join",
    "admin": false,
    "required": [],
    "optional": [],
    "description": "Enrolls/Unenrolls a guild roster member for the current expedition."
  },
  {
    "name": "joined/pool",
    "admin": false,
    "required": [],
    "optional": [],
    "description": "Lists all members that have joined the current expedition."
  },
  {
    "name": "lt3/roster",
    "admin": false,
    "required": [],
    "optional": [],
    "description": "Lists everyone on the guild roster."
  },
  {
    "name": "add",
    "admin": true,
    "required": ["Discord ID", "Name", "Class", "Rating [1-10]"],
    "optional": [],
    "description": "Adds a member to the guild roster."
  },
  {
    "name": "demote",
    "admin": true,
    "required": ["Name"],
    "optional": [],
    "description": "Demotes a leader to a member."
  },
  {
    "name": "find",
    "admin": true,
    "required": ["Name"],
    "optional": [],
    "description": "Lists details for a guild roster member."
  },
  {
    "name": "promote",
    "admin": true,
    "required": ["Name"],
    "optional": [],
    "description": "Promotes a member to a leader."
  },
  {
    "name": "remove",
    "admin": true,
    "required": ["Name"],
    "optional": [],
    "description": "Removes a member from the guild roster."
  },
  {
    "name": "reset",
    "admin": true,
    "required": [],
    "optional": [],
    "description": "The expedition groups are reset."
  },
  {
    "name": "timerChAdd",
    "admin": true,
    "required": [],
    "optional": [],
    "description": "Adds the current channel to the timers list."
  },
  {
    "name": "timerChList",
    "admin": true,
    "required": [],
    "optional": [],
    "description": "Lists all channels in the timers list."
  },
  {
    "name": "timerChRemove",
    "admin": true,
    "required": [],
    "optional": [],
    "description": "Removes the current channel from the timers list."
  }
]
